pcaspy/__init__.py
pcaspy/_cas.cp35-win_amd64.pyd
pcaspy/_version.py
pcaspy/alarm.py
pcaspy/cas.py
pcaspy/driver.py
pcaspy/tools.py
pcaspy-0.8.1.dist-info/LICENSE
pcaspy-0.8.1.dist-info/METADATA
pcaspy-0.8.1.dist-info/WHEEL
pcaspy-0.8.1.dist-info/top_level.txt
pcaspy-0.8.1.dist-info/RECORD
