Metadata-Version: 2.1
Name: pcaspy
Version: 0.8.1
Summary: Portable Channel Access Server in Python
Home-page: https://pypi.python.org/pypi/pcaspy
Author: Xiaoqiang Wang
Author-email: xiaoqiangwang@gmail.com
License: BSD
Platform: Windows
Platform: Linux
Platform: Mac OS X
Classifier: Development Status :: 4 - Beta
Classifier: Environment :: Console
Classifier: Intended Audience :: Developers
Classifier: License :: OSI Approved :: BSD License
Classifier: Programming Language :: C++
Classifier: Programming Language :: Python :: 2
Classifier: Programming Language :: Python :: 3
